cesg/ConditionalEvidenceStream.py
cesg/__init__.py
cesg/_version.py
cesg/concepts.py
cesg/utils.py
cesg-1.0.0.dist-info/METADATA
cesg-1.0.0.dist-info/WHEEL
cesg-1.0.0.dist-info/top_level.txt
cesg-1.0.0.dist-info/RECORD
