Metadata-Version: 2.1
Name: cesg
Version: 1.0.0
Summary: Data stream generator for *Certainty-based Domain Selection Framework for TinyML Devices* paper.
Home-page: https://github.com/w4k2/cesg
Download-URL: https://github.com/w4k2/cesg
Maintainer: P. Ksieniewicz
Maintainer-email: pawel.ksieniewicz@pwr.edu.pl
License: GPL-3.0
Classifier: Development Status :: 4 - Beta
Classifier: Intended Audience :: Science/Research
Classifier: License :: OSI Approved :: GNU General Public License v3 (GPLv3)
Classifier: Programming Language :: Python
Classifier: Programming Language :: Python :: 3.7
Classifier: Topic :: Scientific/Engineering
Classifier: Topic :: Scientific/Engineering :: Artificial Intelligence
Classifier: Topic :: Software Development :: Libraries
Classifier: Topic :: Software Development :: Libraries :: Python Modules
Requires-Dist: numpy
Requires-Dist: scipy
Requires-Dist: scikit-learn
Requires-Dist: stream-learn
